topsis/__init__.py
topsis/topsis_nitanshjain_102017025.py
topsis_nitanshjain_102017025-0.1.2.dist-info/METADATA
topsis_nitanshjain_102017025-0.1.2.dist-info/WHEEL
topsis_nitanshjain_102017025-0.1.2.dist-info/entry_points.txt
topsis_nitanshjain_102017025-0.1.2.dist-info/top_level.txt
topsis_nitanshjain_102017025-0.1.2.dist-info/RECORD
