Metadata-Version: 2.1
Name: topsis-nitanshjain-102017025
Version: 0.1.2
Summary: Topsis Calculation Package
Author: Nitansh Jain
Author-email: <njain_be20@thapar.edu>
Keywords: python,topsis,mcdm
Classifier: Development Status :: 1 - Planning
Classifier: Intended Audience :: Developers
Classifier: Programming Language :: Python :: 3
Classifier: Operating System :: Unix
Classifier: Operating System :: MacOS :: MacOS X
Classifier: Operating System :: Microsoft :: Windows
Requires-Dist: pandas
Requires-Dist: numpy
Requires-Dist: detect-delimiter
Requires-Dist: scipy
